README.rst
setup.cfg
setup.py
doctests/__init__.py
fuel/__init__.py
fuel/config_parser.py
fuel/exceptions.py
fuel/iterator.py
fuel/schemes.py
fuel/server.py
fuel/streams.py
fuel/version.py
fuel.egg-info/PKG-INFO
fuel.egg-info/SOURCES.txt
fuel.egg-info/dependency_links.txt
fuel.egg-info/entry_points.txt
fuel.egg-info/requires.txt
fuel.egg-info/top_level.txt
fuel/bin/__init__.py
fuel/bin/fuel_convert.py
fuel/bin/fuel_download.py
fuel/bin/fuel_info.py
fuel/converters/__init__.py
fuel/converters/adult.py
fuel/converters/base.py
fuel/converters/binarized_mnist.py
fuel/converters/caltech101_silhouettes.py
fuel/converters/celeba.py
fuel/converters/cifar10.py
fuel/converters/cifar100.py
fuel/converters/dogs_vs_cats.py
fuel/converters/ilsvrc2010.py
fuel/converters/iris.py
fuel/converters/mnist.py
fuel/converters/svhn.py
fuel/converters/youtube_audio.py
fuel/datasets/__init__.py
fuel/datasets/adult.py
fuel/datasets/base.py
fuel/datasets/billion.py
fuel/datasets/binarized_mnist.py
fuel/datasets/caltech101_silhouettes.py
fuel/datasets/celeba.py
fuel/datasets/cifar10.py
fuel/datasets/cifar100.py
fuel/datasets/dogs_vs_cats.py
fuel/datasets/hdf5.py
fuel/datasets/imagenet.py
fuel/datasets/iris.py
fuel/datasets/mnist.py
fuel/datasets/svhn.py
fuel/datasets/text.py
fuel/datasets/toy.py
fuel/datasets/youtube_audio.py
fuel/downloaders/__init__.py
fuel/downloaders/adult.py
fuel/downloaders/base.py
fuel/downloaders/binarized_mnist.py
fuel/downloaders/caltech101_silhouettes.py
fuel/downloaders/celeba.py
fuel/downloaders/cifar10.py
fuel/downloaders/cifar100.py
fuel/downloaders/dogs_vs_cats.py
fuel/downloaders/ilsvrc2010.py
fuel/downloaders/iris.py
fuel/downloaders/mnist.py
fuel/downloaders/svhn.py
fuel/downloaders/youtube_audio.py
fuel/transformers/__init__.py
fuel/transformers/_image.c
fuel/transformers/defaults.py
fuel/transformers/image.py
fuel/transformers/text.py
fuel/utils/__init__.py
fuel/utils/formats.py
fuel/utils/parallel.py
tests/converters/__init__.py
tests/converters/test_convert_ilsvrc2010.py
tests/transformers/__init__.py
tests/transformers/test_image.py
tests/transformers/test_transformers.py