Metadata-Version: 1.1
Name: fuel
Version: 0.2.0
Summary: Data pipeline framework for machine learning
Home-page: https://github.com/mila-udem/fuel.git
Author: Universite de Montreal
Author-email: UNKNOWN
License: MIT
Download-URL: https://github.com/mila-udem/fuel/archive/0.2.0tar.gz
Keywords: dataset data iteration pipeline processing
Platform: UNKNOWN
Classifier: Development Status :: 3 - Alpha
Classifier: Intended Audience :: Developers
Classifier: Topic :: Utilities
Classifier: Topic :: Scientific/Engineering
Classifier: License :: OSI Approved :: MIT License
Classifier: Programming Language :: Python :: 2
Classifier: Programming Language :: Python :: 2.7
Classifier: Programming Language :: Python :: 3
Classifier: Programming Language :: Python :: 3.4
